odoo/addons/base_db_anonymization/LICENSE
odoo/addons/base_db_anonymization/README.rst
odoo/addons/base_db_anonymization/__init__.py
odoo/addons/base_db_anonymization/__manifest__.py
odoo/addons/base_db_anonymization/data/ir_model_fields.xml
odoo/addons/base_db_anonymization/demo/res_groups.xml
odoo/addons/base_db_anonymization/images/screen.png
odoo/addons/base_db_anonymization/models/__init__.py
odoo/addons/base_db_anonymization/models/ir_model_fields.py
odoo/addons/base_db_anonymization/security/ir.model.access.csv
odoo/addons/base_db_anonymization/security/security.xml
odoo/addons/base_db_anonymization/static/description/icon.png
odoo/addons/base_db_anonymization/static/description/index.html
odoo/addons/base_db_anonymization/views/ir_model_fields.xml
odoo/addons/base_db_anonymization/views/ir_models_fields_anonymize.xml
odoo_addon_base_db_anonymization-18.0.1.4.0.1.dist-info/METADATA
odoo_addon_base_db_anonymization-18.0.1.4.0.1.dist-info/WHEEL
odoo_addon_base_db_anonymization-18.0.1.4.0.1.dist-info/top_level.txt
odoo_addon_base_db_anonymization-18.0.1.4.0.1.dist-info/RECORD
