Metadata-Version: 2.1
Name: odoo-addon-base_db_anonymization
Version: 18.0.1.4.0.1
Requires-Python: >=3.10
Requires-Dist: odoo==18.0.*
Summary: Anonymize content of selected database fields.
Home-page: https://www.mint-system.ch/
License: AGPL-3
Author: Mint System GmbH
Classifier: Programming Language :: Python
Classifier: Framework :: Odoo
Classifier: Framework :: Odoo :: 18.0
Classifier: License :: OSI Approved :: GNU Affero General Public License v3
